{
  "$schema": "https://turbo.build/schema.v2.json",
  "ui": "tui",
  "tasks": {
    "build": {
      "dependsOn": ["^build"],
      "outputs": ["dist/**"]
    },
    "clean:build": {
      "cache": false
    },
    "clean:cache": {
      "cache": false
    },
    "//#clean:cache:root": {
      "cache": false
    },
    "clean:turbo": {
      "cache": false
    },
    "//#clean:turbo:root": {
      "cache": false
    },
    "format:eslint": {
      "dependsOn": [
        "@incentro-ic/config-cspell#build",
        "@incentro-ic/config-eslint#build"
      ]
    },
    "format:prettier": {},
    "//#format:prettier:root": {},
    "lint:eslint": {
      "dependsOn": [
        "@incentro-ic/config-cspell#build",
        "@incentro-ic/config-eslint#build"
      ]
    },
    "lint:prettier": {},
    "//#lint:prettier:root": {},
    "lint:typescript": {},
    "serve": {
      "dependsOn": ["build"],
      "persistent": true
    },
    "start": {
      "dependsOn": ["^build"],
      "persistent": true
    }
  }
}
